duckcuts/.DS_Store
duckcuts/__about__.py
duckcuts/__init__.py
duckcuts/entry_points.py
duckcuts/main.css
duckcuts/main.py
duckcuts/data/.DS_Store
duckcuts/data/terminal.json
duckcuts/data/vim-multiple-files.json
duckcuts/data/vim-operators.json
duckcuts/data/vim-search-replace.json
duckcuts/data/vim-text-objects.json
duckcuts/data/vim.json
duckcuts-1.0.11.dist-info/METADATA
duckcuts-1.0.11.dist-info/WHEEL
duckcuts-1.0.11.dist-info/entry_points.txt
duckcuts-1.0.11.dist-info/RECORD
