Metadata-Version: 2.1
Name: duckcuts
Version: 1.0.11
Summary: A TUI application to help you learn and remember shortcuts for various software.
Project-URL: Homepage, https://dc.vikbytes.com
Author-email: vikbytes <55359319+vikbytes@users.noreply.github.com>
License-Expression: MIT
Classifier: Operating System :: OS Independent
Classifier: Programming Language :: Python :: 3
Requires-Python: >=3.8
Requires-Dist: rich==13.7.0
Requires-Dist: textual==0.48.1
